[{"description": "(江子翠捷運站)板橋早午餐-王樣輕食廚房.搬遷新址,美味法式吐司 新北板橋早午餐店家大集合懶人包(持續增加中) 王樣輕食廚房220新北市板橋區文化路二段182巷...", "phone": "0222578290", "lng": 121.4721611, "blog_type": 0, "lat": 25.0274367, "date": 1489766437.0, "status": 0, "ranking": {}, "location": [121.4721611, 25.0274367], "price": 0, "deal": null, "id": "58cd365d573d05c44c810e93", "is_paid": false, "url": "http://liaa8627.pixnet.net/blog/post/458010254", "thumb": "https://lh3.googleusercontent.com/bF7eFRMdxRxfRvmEJ8ju8FWdUjmEpkv27wRnY9HhRldNr-V8EwYa3DC1Qddn_zC_V__AhNpIFJqVFGlNnrzaXYAxBqBlxkI=s600", "posts": [], "source": "http://liaa8627.pixnet.net/", "rating": 1.76, "area": "板橋區", "stat": {"blog_id": "58cd365d573d05c44c810e93", "share_cnt": 0, "recommend_cnt": 1, "favorite_cnt": 6, "browse_cnt": 159}, "address": "新北市板橋區文化路二段182巷7弄9之1號", "tracking": false, "user": {"display_name": "Nancy將的生活筆計本", "thumb": "https://graph.facebook.com/v2.6/1091227100903216/picture?type=normal", "follower_cnt": 2525, "checkin_cnt": 695, "fav_cnt": 103, "post_cnt": 732, "profile_pic_origin": "https://graph.facebook.com/v2.6/1091227100903216/picture?width=800&height=800", "certified": true, "cover_url": "https://scontent.xx.fbcdn.net/v/t1.0-0/p240x240/942216_1394425397250050_7719434922051956383_n.jpg?oh=874eb7d98a0254176a947034f2753e8c&oe=593987DB", "profile_pic": "https://graph.facebook.com/v2.6/1091227100903216/picture?type=large", "is_following": false, "is_vip": false, "id": "54d831152756dd62678a145e", "following_cnt": 16, "browse_cnt": 583747}, "use_read": true, "restaurant": {"phone": "0222578290", "lng": 121.4722803, "avg_price": 0, "rating": 4.2, "lat": 25.027568, "opening_hours": "今日營業: 08:00-18:00", "cover_url": "https://lh3.googleusercontent.com/gRXwtl6bAO3qYnE__NgcPwXg4rxmoJ0DmRxxqkvyUM31pnRHGY_rssQPo4QQjOqrMoYX2af3xszArY-dTQWvE-bDcM1X1ZI=s600", "name": "王樣輕食廚房", "id": "559bfff2c03a101f6d8b79c8", "address": "新北市板橋區市文化路二段182巷3弄95號", "last_visit": 1489766427.0, "blog_cnt": 4, "city": "新北市", "visit_cnt": 5, "admin_name": "板橋區", "cover_author": "35號的腳印"}, "city": "新北市", "title": "板橋早午餐-王樣輕食廚房.搬遷新址,美味法式吐司", "author": "Nancy將", "tracking_id": null}, {"description": "昨天娘娘根據美食情報員告知，得知內湖區最近新開了一家燒燙燙的紅牌名店，剛剛好又在我家不遠處，擇日不如撞日～今天就前往一探究竟。", "phone": "0227990567", "lng": 121.5761403, "blog_type": 0, "lat": 25.0766588, "date": 1489766435.0, "status": 201, "ranking": {}, "location": [121.5761403, 25.0766588], "price": 200, "deal": null, "id": "58cc1fe223679c33f600644b", "is_paid": false, "url": "http://a0809915021.pixnet.net/blog/post/302792935-%5b大腳娘娘在台北%5d-強棒出擊～！！”初牛“丼", "thumb": "https://lh3.googleusercontent.com/G4k4YpcuMsYwFWRzOsufUAF5-7KcLFmHMR5A2ExJN5JzucKV5JXbt_ov51RK1MXcVBoI59S3QvXyFU4MM0sdiLRcpmbZLg=s600", "posts": [], "source": "577afbf0699b6e5943920faa", "rating": 2.15, "area": "內湖區", "stat": {"blog_id": "58cc1fe223679c33f600644b", "share_cnt": 0, "recommend_cnt": 1, "favorite_cnt": 17, "browse_cnt": 335}, "address": "臺北市內湖區江南街116巷1號", "tracking": false, "user": {"display_name": "大腳娘娘吃遊記", "thumb": "https://lh3.googleusercontent.com/pubLvtY_mbpnFIsIU9q_NrBnYvqQeD4bctCu8T7QSEBgVU4-hhHDI5SHSQvr3COnQ-9eozl5dB-OPdtuPZylTrPRXOH-tA=s600", "follower_cnt": 34, "checkin_cnt": 18, "fav_cnt": 5, "post_cnt": 18, "profile_pic_origin": "https://lh3.googleusercontent.com/pubLvtY_mbpnFIsIU9q_NrBnYvqQeD4bctCu8T7QSEBgVU4-hhHDI5SHSQvr3COnQ-9eozl5dB-OPdtuPZylTrPRXOH-tA=s600", "certified": true, "cover_url": "https://scontent.xx.fbcdn.net/v/t1.0-9/s720x720/12924420_1131502586880856_6049582080691233394_n.jpg?oh=cf8cf530dbbe221ee5fcba95a538ffb6&oe=58001C4D", "profile_pic": "https://lh3.googleusercontent.com/pubLvtY_mbpnFIsIU9q_NrBnYvqQeD4bctCu8T7QSEBgVU4-hhHDI5SHSQvr3COnQ-9eozl5dB-OPdtuPZylTrPRXOH-tA=s600", "is_following": false, "is_vip": false, "id": "577afbf0699b6e5943920faa", "following_cnt": 22, "browse_cnt": 8790}, "use_read": true, "restaurant": {"phone": "0227990567", "lng": 121.5761403, "avg_price": 200, "rating": 4.7, "lat": 25.0766588, "opening_hours": "今日營業: 11:30-14:00, 17:30-21:00", "cover_url": "https://lh3.googleusercontent.com/-r1syvChUTEpHvDaxFZy8VT-TCst4rHmRjT8mPnpoEjCictqJmAZh2Dpr0ATkOw12r4wKLcR5g3BoOdYDo9mQA6HLIFqnioZ=s600", "name": "初牛炭火直燒 (江南店)", "id": "585d68c72756dd7579b8f332", "address": "臺北市內湖區江南街116巷1號", "last_visit": 1489795200.0, "blog_cnt": 4, "city": "台北市", "visit_cnt": 9, "admin_name": "內湖區", "cover_author": "老K"}, "city": "台北市", "title": "”初牛“丼飯專賣店，找回對牛肉最初的愛～ ", "author": "大腳娘娘吃遊記", "tracking_id": null}, {"description": "一般人對菜市場的想像都是吵雜人多，而位在三峽公有市場三樓的「咖啡瑀」讓妳顛覆傳統，這座在地三峽人的市場內有四個樓層，依照不同屬性的攤位分散在不同層，怎麼會有咖啡...", "phone": "02-86720204", "lng": 121.3710938, "blog_type": 0, "lat": 24.9348402, "date": 1489766434.0, "status": 0, "ranking": {}, "location": [121.3710938, 24.9348402], "price": 0, "deal": null, "id": "58cd35b55069ac634c2db1ca", "is_paid": false, "url": "http://iting35.pixnet.net/blog/post/221934911-%e3%80%90%e4%b8%89%e5%b3%bd%e3%80%91%e5%85%ac%e6%9c%89%e5%b8%82%e5%a0%b4%e8%a3%a1%e7%9a%84%e7%b5%95%e5%a6%99%e5%a5%bd%e5%92%96%e5%95%a1%7e%e5%92%96%e5%95%a1%e7%91%80%e8%87%aa", "thumb": "https://lh3.googleusercontent.com/1ZAHPsY_2y8msQzcZLCfb3iF7YZsyqZ2owMkWEO8L8aL7dTS4rxRtFvHPHsR4LyL8vymz_a4LWaGJxfqnbKDjdtC_1YtxKI=s600", "posts": [], "source": "http://iting35.pixnet.net/", "rating": 1.84, "area": "三峽區", "stat": {"blog_id": "58cd35b55069ac634c2db1ca", "share_cnt": 0, "recommend_cnt": 1, "favorite_cnt": 7, "browse_cnt": 174}, "address": "新北市三峽區民生路183號B3樓", "tracking": false, "user": {"display_name": "35號的腳印", "thumb": "https://farm9.staticflickr.com/8756/17054989848_c8b4acf1b4_n.jpg", "follower_cnt": 1967, "checkin_cnt": 793, "fav_cnt": 0, "post_cnt": 824, "profile_pic_origin": "https://farm9.staticflickr.com/8756/17054989848_c8b4acf1b4_n.jpg", "certified": true, "cover_url": "https://farm9.staticflickr.com/8726/17242749045_d7a48825bd_o.jpg", "profile_pic": "https://farm9.staticflickr.com/8756/17054989848_c8b4acf1b4_n.jpg", "is_following": false, "is_vip": false, "id": "5538b2f9699b6e504c2b952e", "following_cnt": 0, "browse_cnt": 396905}, "use_read": true, "restaurant": {"phone": null, "lng": 121.3710488, "avg_price": 0, "rating": 3.9, "lat": 24.934952, "opening_hours": "尚無營業時間資訊", "cover_url": "https://lh3.googleusercontent.com/1ZAHPsY_2y8msQzcZLCfb3iF7YZsyqZ2owMkWEO8L8aL7dTS4rxRtFvHPHsR4LyL8vymz_a4LWaGJxfqnbKDjdtC_1YtxKI=s600", "name": "三峽公有市場", "id": "58cd77b12756dd602f419ce1", "address": "新北市三峽區民生路183號B3樓", "last_visit": 1489766424.0, "blog_cnt": 1, "city": "新北市", "visit_cnt": 1, "admin_name": "三峽區", "cover_author": "35號的腳印"}, "city": "新北市", "title": "公有市場裡的絕妙好咖啡~咖啡瑀自家焙煎咖啡", "author": "35號的腳印", "tracking_id": null}, {"description": "已經進入春天了，不過有時還會感受到些許的寒意，此時來品嚐暖呼呼的火鍋，是最幸福不過的事情了。此篇寶小銘分享給大家的是「HELLO KITTY Shabu-Shabu」，除了提供多樣溫暖的鍋物外，還有HELLO KITTY陪用餐，讓整體用餐氛圍更顯得溫馨十足。", "phone": "0227115216", "lng": 121.5539231, "blog_type": 0, "lat": 25.0398368, "date": 1489766433.0, "status": 201, "ranking": {}, "location": [121.5539231, 25.0398368], "price": 500, "deal": null, "id": "58cc2740699b6e28b53b1de4", "is_paid": false, "url": "https://ifoodie.tw/post/58cc2740699b6e28b53b1de4", "thumb": "https://lh3.googleusercontent.com/NYzMlRlC9ppLtV3BC4rbJr6SC3BW88Yz88RqsRu7jw3nz6gMTol38dRtAoyx8tWL2Zs74IlcL3cIrqibshWk5VfmDWGhDQ=s600", "posts": [], "source": "57e81b7023679c0fc40a31dd", "rating": 3.47, "area": "大安區", "stat": {"blog_id": "58cc2740699b6e28b53b1de4", "share_cnt": 2, "recommend_cnt": 1, "favorite_cnt": 10, "browse_cnt": 150}, "address": "臺北市大安區忠孝東路四段216巷27弄16號", "tracking": false, "user": {"display_name": "寶小銘", "thumb": "https://lh3.googleusercontent.com/kX-wuui7zkBeY2kj4KaHeGTOYMdXhamelnTi1m1KkOGm5Db0i7IXzhyza3iwoJSBNjc1M-VRv3HzDmFQDZYqCZDFcUIWvNE=s600", "follower_cnt": 38, "checkin_cnt": 20, "fav_cnt": 0, "post_cnt": 20, "profile_pic_origin": "https://lh3.googleusercontent.com/kX-wuui7zkBeY2kj4KaHeGTOYMdXhamelnTi1m1KkOGm5Db0i7IXzhyza3iwoJSBNjc1M-VRv3HzDmFQDZYqCZDFcUIWvNE=s600", "certified": true, "cover_url": "https://lh3.googleusercontent.com/_DOq_CU52XZLmuTZAZAap8ElE06Gr5ZUxUS3sUWvjsKGwrQGkd9WAzRAeJir8SaS_CtJ0AHJODH_VjR0IgUXmraH5mQdoOc=s600", "profile_pic": "https://lh3.googleusercontent.com/kX-wuui7zkBeY2kj4KaHeGTOYMdXhamelnTi1m1KkOGm5Db0i7IXzhyza3iwoJSBNjc1M-VRv3HzDmFQDZYqCZDFcUIWvNE=s600", "is_following": false, "is_vip": false, "id": "57e81b7023679c0fc40a31dd", "following_cnt": 10, "browse_cnt": 3275}, "use_read": true, "restaurant": {"phone": "0227115216", "lng": 121.5539231, "avg_price": 500, "rating": 3.6, "lat": 25.0398368, "opening_hours": "今日營業: 11:30-22:00", "cover_url": "https://lh3.googleusercontent.com/XAiuiuLP37_uI3IXRxxW5lTJFfjkXMCLOtJf79nXIyIzHmSkReRV29LciLq0vkRA_xlfDfCo92syIQwUAkZZDdcw92GLSEg=s600", "name": "Hello Kitty火鍋", "id": "559dd697c03a103ee86cb229", "address": "臺北市大安區忠孝東路四段216巷27弄16號", "last_visit": 1489795200.0, "blog_cnt": 26, "city": "台北市", "visit_cnt": 41, "admin_name": "大安區", "cover_author": "AJ"}, "city": "台北市", "title": "HELLO KITTY Shabu-Shabu (忠孝店）~~暖心又暖胃的鍋物．療癒感十足的KITTY陪用餐", "author": "寶小銘", "tracking_id": null}, {"description": "今年新開幕的345美式複合餐廳，就在新莊捷運站走路大約6分鐘左右的距離，鄰近新莊體育場、輔仁大學，過對面馬路就是W先生說新莊唯一好吃日本料理的鮭鮮人，說要來結果...", "phone": "0222066890", "lng": 121.4474404, "blog_type": 0, "lat": 25.0349209, "date": 1489766432.0, "status": 0, "ranking": {}, "location": [121.4474404, 25.0349209], "price": 0, "deal": null, "id": "58cd35835069ac634c2db1c3", "is_paid": false, "url": "http://hurainjay.pixnet.net/blog/post/221881799", "thumb": "https://lh3.googleusercontent.com/_XrJ3Q0HYlTjci3YsSk3b0clsG4FL_ov7AqLgSF3GT-7n6hGrteaSPmEkkQHp6wQzK1df_7UxEDDZBgVfQJ-a8D2D_hJuw=s600", "posts": [], "source": "http://hurainjay.pixnet.net/", "rating": 3.16, "area": "新莊區", "stat": {"blog_id": "58cd35835069ac634c2db1c3", "share_cnt": 3, "recommend_cnt": 1, "favorite_cnt": 10, "browse_cnt": 177}, "address": "新北市新莊區中正路345號", "tracking": false, "user": {"display_name": "烏娜小姐", "thumb": "https://farm8.staticflickr.com/7553/16264430906_bc5db2c31d_n.jpg", "follower_cnt": 2753, "checkin_cnt": 419, "fav_cnt": 92, "post_cnt": 406, "profile_pic_origin": "https://farm8.staticflickr.com/7553/16264430906_bc5db2c31d_n.jpg", "certified": true, "cover_url": "https://farm8.staticflickr.com/7558/16102828868_5a5440ea1f_z.jpg", "profile_pic": "https://farm8.staticflickr.com/7553/16264430906_bc5db2c31d_n.jpg", "is_following": false, "is_vip": false, "id": "54870c2ad4fdab2441abd0c9", "following_cnt": 4, "browse_cnt": 335027}, "use_read": true, "restaurant": {"phone": "0222066890", "lng": 121.44745, "avg_price": 0, "rating": 5.0, "lat": 25.03496059999999, "opening_hours": "今日營業: 11:00-22:00", "cover_url": "https://lh3.googleusercontent.com/zISkHf0mMKQf37RX9AGbLeKxVE1Lou0xiPtmxO84PAO3phc1rzGKU0_sq2lPTArsXSaaZXS6jRUY8GNvpjwfPu02IUbsOA=s600", "name": "345美式複合餐廳", "id": "58c6df2e2756dd602f4198d6", "address": "新北市新莊區中正路345號", "last_visit": 1489766429.0, "blog_cnt": 3, "city": "新北市", "visit_cnt": 3, "admin_name": "新莊區", "cover_author": "小妞的生活旅程"}, "city": "新北市", "title": "捷運新莊站 345美式複合餐廳 燉飯/義大利麵/帕里尼 （免收服務費）", "author": "烏娜小姐", "tracking_id": null}]